Metadata-Version: 1.0
Name: Flask-Github
Version: 0.1.2
Summary: Adds support for authorizing users with Github to Flask
Home-page: http://github.com/jarodl/flask-github
Author: Jarod Luebbert
Author-email: jarodluebbert@gmail.com
License: MIT
Platform: any
Classifier: Environment :: Web Environment
Classifier: Intended Audience :: Developers
Classifier: Operating System :: OS Independent
Classifier: Programming Language :: Python
Classifier: Topic :: Internet :: WWW/HTTP :: Dynamic Content
Classifier: Topic :: Software Development :: Libraries :: Python Modules
